{
  "schemaVersion": 1,
  "id": "jilibs-pressure",
  "name": "Ji Libs Pressure",
  "description": "Contains the essential API for handling pressure.",
  "version": "${version}",
  "environment": "*",
  "mixins": [
    "jilibs-pressure.mixins.json"
  ],
  "license": "MIT",
  "icon": "assets/jilibs-pressure/icon.png",
  "contact": {
    "homepage": "https://www.youtube.com/@TheMentorCodeLab",
    "issues": "https://github.com/drkhodakarami/JiLibs/issues",
    "sources": "https://github.com/drkhodakarami/JiLibs"
  },
  "authors": [
    "The Mentor"
  ],
  "depends": {
    "fabricloader": ">=${loader_version}",
    "minecraft": "~${game_version}",
    "java": ">=${java_version}",
    "fabric-api": "*"
  }
}